[
  {
    "id": 41780,
    "name": "캐럿글로벌",
    "image": "https://daoift3qrrnil.cloudfront.net/employment_companies/images/000/041/780/original/carrot.png?1612147765",
    "start_time": "2022-02-01T10:29:00.000+09:00",
    "end_time": "2022-02-28T23:59:00.000+09:00",
    "content": "<p style=\"text-align: center;\"><img alt=\"\" src=\"https://daoift3qrrnil.cloudfront.net/home/ec2-user/jasoseol/public/ckeditor_assets/pictures/55562/content_-_210201.jpg\" style=\"width: 800px; height: 9561px;\" /></p>\r\n"
  },
  {
    "id": 41794,
    "name": "펑타이코리아",
    "image": "https://daoift3qrrnil.cloudfront.net/employment_companies/images/000/041/794/original/_PTK_Brandmark_black_%281%29.png?1612171640",
    "start_time": "2022-02-01T17:15:00.000+09:00",
    "end_time": "2022-02-12T22:00:00.000+09:00",
    "content": "<div style=\"border: 1px solid #ddd; color: #333; font-size: 15px; word-break: break-word;\">\r\n<div style=\"padding: 6%;\">\r\n<div style=\"border: 1px solid #ddd; background: #fafafa; padding: 10px; text-align: center; font-size: 20px; color: #000; font-weight: bold;\">[펑타이코리아] 온라인 기획 및 지원 인턴</div>\r\n\r\n<div style=\"display: flex; justify-content: center; align-items: center; height: 150px; margin: 14% auto;\"><img src=\"https://daoift3qrrnil.cloudfront.net/home/ec2-user/jasoseol/public/ckeditor_assets/pictures/55553/content_ptk_brandmark_black_1.png\" style=\"max-height: 120px; max-width: 40% !important; width: 100px; height: 71px;\" /></div>\r\n\r\n<div style=\"color: #000;\">\r\n<div>펑타이 코리아는 2020년 현재 총 400 여 명의 디지털 전문가로 구성되어 있으며, 한국을 비롯해 중국, 일본, 동남아, 남미, 유럽 등 글로벌 각국의 고객을 위해 일하고 있습니다. 성공적인 비즈니스를 위한 &lsquo;통합 디지털 마케팅 솔루션&rsquo;을 제공하는 우리의 철학, CI, 그리고 리더십을 소개합니다.</div>\r\n\r\n<div>&nbsp;</div>\r\n\r\n<div>펑타이는 고객의 성장을 가장 먼저 생각합니다. 그리고 우리 스스로와 세상을 함께 성장으로 이끄는 방법에 대해 고민합니다. 그 해답을 디지털에서 찾는 우리는 데이터, 테크놀로지, 크리에이티브의 융합을 통해 시대의 빠른 변화에도 지속 가능한 성장의 솔루션을 제시합니다.</div>\r\n</div>\r\n</div>\r\n\r\n<div style=\"padding: 6%; border-top: 1px solid #ddd; border-bottom: 1px solid #ddd;\">\r\n<div style=\"font-size: 16px; color: #000; font-weight: bold; margin-bottom: 10px;\">&bull; 모집 직무</div>\r\n\r\n<div style=\"margin-bottom: 20px;\">\r\n<div style=\"font-size: 16px; color: #000; font-weight: bold;\">온라인 기획 및 지원 인턴 (인턴)</div>\r\n\r\n<div style=\"margin-top: 10px;\">\r\n<div>[담당업무]</div>\r\n\r\n<div>- 온라인 제품 페이지( 글로벌 사이트 및 일부 거래선 사이트) 모니터링 수행</div>\r\n\r\n<div>- 글로벌네트워크 거래선 사이트 모니터링 결과 취합 및 검증</div>\r\n\r\n<div>- 월별 모니터링 항목, 대상제품 리스트 관리</div>\r\n\r\n<div>- 엑셀, 파워포인트 리포트 문서 작성</div>\r\n\r\n<div>&nbsp;</div>\r\n\r\n<div>[자격요건]</div>\r\n\r\n<div>- 엑셀 능숙, 데이터 취합&amp;관리</div>\r\n\r\n<div>- 국/영문 문서작업 경험자</div>\r\n\r\n<div>- 꼼꼼한 성향, 책임감</div>\r\n</div>\r\n</div>\r\n</div>\r\n\r\n<div style=\"padding: 6%;\">\r\n<div style=\"font-size: 16px; color: #000; font-weight: bold; margin-bottom: 10px;\">&bull; 근무환경</div>\r\n\r\n<div style=\"margin-bottom: 20px;\">\r\n<div>- 4대보험 가입(국민연금, 건강보험, 고용보험, 산재보험)</div>\r\n\r\n<div>- 임직원 생일축하 비용 지원 / 명절 선물 지급</div>\r\n\r\n<div>- 중식비 일부 지원</div>\r\n\r\n<div>- 마이데이(월 1회 한 시간 조기 퇴근 또는 1시간 늦은 출근)</div>\r\n\r\n<div>- 동호회날(매 짝수 달 1회 동호회 활동)</div>\r\n</div>\r\n\r\n<div style=\"font-size: 16px; color: #000; font-weight: bold; margin-bottom: 10px;\">&bull; 접수 경로</div>\r\n\r\n<div style=\"margin-bottom: 20px;\">ptk.recruit@cheilpengtai.com</div>\r\n\r\n<div style=\"font-size: 16px; color: #000; font-weight: bold; margin-bottom: 10px;\">&bull; 제출 서류</div>\r\n\r\n<div style=\"margin-bottom: 20px;\">국문 이력서, 자기소개서(자유형태)</div>\r\n\r\n<div style=\"font-size: 16px; color: #000; font-weight: bold; margin-bottom: 10px;\">&bull; 문의처</div>\r\n\r\n<div>ptk.recruit@cheilpengtai.com</div>\r\n</div>\r\n</div>\r\n"
  },
  {
    "id": 41817,
    "name": "에코마케팅",
    "image": "https://daoift3qrrnil.cloudfront.net/employment_companies/images/000/041/817/original/ECHO_CI_color.jpg?1612243127",
    "start_time": "2022-02-02T12:02:00.000+09:00",
    "end_time": "2022-03-04T12:02:00.000+09:00",
    "content": "<div><img src=\"https://daoift3qrrnil.cloudfront.net/content_images/images/000/060/918/original/200622_%EA%B8%80%EB%A1%9C%EB%B2%8C%EB%A7%88%EC%BC%80%ED%8C%85_%ED%94%84%EB%9E%91%EC%8A%A4%EC%96%B4_%EC%9D%B8%ED%84%B4.jpg?1612235201\" style=\"‘max-width:\" /></div>\r\n"
  },
  {
    "id": 41834,
    "name": "TES",
    "image": "https://daoift3qrrnil.cloudfront.net/employment_companies/images/000/041/834/original/ci150150.png?1612260074",
    "start_time": "2022-02-02T17:35:00.000+09:00",
    "end_time": "2022-02-07T23:59:00.000+09:00",
    "content": "<div><img src=\"https://daoift3qrrnil.cloudfront.net/content_images/images/000/060/952/original/%EA%B3%B5%EA%B3%A02.png?1612255167\" style=\"‘max-width:\" /></div>\r\n"
  },
  {
    "id": 41857,
    "name": "대흥알앤티",
    "image": "https://daoift3qrrnil.cloudfront.net/employment_companies/images/000/041/857/original/logo_460.jpg?1612331845",
    "start_time": "2022-02-03T14:52:00.000+09:00",
    "end_time": "2022-02-16T23:59:00.000+09:00",
    "content": "<p style=\"text-align: center;\"><img alt=\"\" src=\"https://daoift3qrrnil.cloudfront.net/home/ec2-user/jasoseol/public/ckeditor_assets/pictures/55583/content_.png.\" style=\"width: 800px; height: 3378px;\" /></p>\r\n"
  },
  {
  "id": 41960,
  "name": "한국광기술원",
  "image": "https://daoift3qrrnil.cloudfront.net/employment_companies/images/000/041/960/original/%EC%9D%B4%EB%AF%B8%EC%A7%80_4.png?1612758804",
  "start_time": "2022-02-08T09:00:00.000+09:00",
  "end_time": "2022-03-04T17:00:00.000+09:00",
  "content": "<p><img src=\"https://kopti.recruiter.co.kr/upload/121424/image/202202/cbff3413-b82d-4c78-a5fe-ab371b2a5b6f.jpg\" style=\"height: auto; max-width: 100%;\" title=\"2022년_1차_계약직_채용공고(안)001.jpg\" /></p>\r\n\r\n<p>&nbsp;</p>\r\n"
  },
  {
  "id": 41962,
  "name": "KT스카이라이프",
  "image": "https://daoift3qrrnil.cloudfront.net/employment_companies/images/000/041/962/original/data?1612753821",
  "start_time": "2022-02-08T12:00:00.000+09:00",
  "end_time": "2022-02-24T23:55:00.000+09:00",
  "content": "<p>&nbsp;</p>\r\n\r\n<p><img src=\"https://kt.recruiter.co.kr/upload/33092/image/202202/d82081a9-96a9-43bf-8079-49900b18365c.jpg\" style=\"max-width:100%; height:auto;\" title=\"채용공고이미지_v2.jpg\" /></p>\r\n\r\n<p>&nbsp;</p>\r\n\r\n<p>&nbsp;</p>\r\n\r\n<p>&nbsp;</p>\r\n"
  },
  {
  "id": 42018,
  "name": "이랜드파크",
  "image": "https://daoift3qrrnil.cloudfront.net/employment_companies/images/000/042/018/original/data?1612840212",
  "start_time": "2022-02-09T00:00:00.000+09:00",
  "end_time": "2022-02-21T00:00:00.000+09:00",
  "content": "<p><img title=\"제목을 입력해주세요._005 (1).jpg\" style=\"height: auto; max-width: 100%;\" src=\"https://elandpark.recruiter.co.kr/upload/100046/image/202202/ec752b07-2554-4da8-944f-e7f97d42d78e.jpg\"><br style=\"clear: both;\"><br style=\"clear: both;\">&nbsp;</p><p>&nbsp;</p>"
  },
  {
  "id": 42124,
  "name": "피앤피시큐어",
  "image": "https://daoift3qrrnil.cloudfront.net/employment_companies/images/000/042/124/original/%ED%94%BC%EC%95%A4%ED%94%BC%EC%8B%9C%ED%81%90%EC%96%B4_%EB%A1%9C%EA%B3%A0_%EB%B3%80%ED%98%95_150px.png?1613380512",
  "start_time": "2022-02-15T16:55:00.000+09:00",
  "end_time": "2022-02-28T23:59:00.000+09:00",
  "content": "<div style=\"border: 1px solid #ddd; color: #333; font-size: 15px; word-break: break-word;\">\r\n<div style=\"padding: 6%;\">\r\n<div style=\"border: 1px solid #ddd; background: #fafafa; padding: 10px; text-align: center; font-size: 20px; color: #000; font-weight: bold;\">[피앤피시큐어] 2022년 부문별 수시채용</div>\r\n\r\n<div style=\"display: flex; justify-content: center; align-items: center; height: 150px; margin: 14% auto;\"><img src=\"https://daoift3qrrnil.cloudfront.net/business_employment_companies/images/000/006/774/original/%ED%94%BC%EC%95%A4%ED%94%BC%EC%8B%9C%ED%81%90%EC%96%B4_%EB%A1%9C%EA%B3%A0_%EB%B3%80%ED%98%95_150px.png?1613376490\" style=\"max-height:120px; max-width:40% !important;\" /></div>\r\n\r\n<div style=\"color: #000;\">\r\n<div>대한민국 정보보안의 미래를 열어갈 다재다능한 인재를 공개 모집합니다.</div>\r\n\r\n<div>도전하고자 하는 분들의 많은 지원을 기다립니다.</div>\r\n</div>\r\n</div>\r\n\r\n<div style=\"padding: 6%; border-top: 1px solid #ddd; border-bottom: 1px solid #ddd;\">\r\n<div style=\"font-size: 16px; color: #000; font-weight: bold; margin-bottom: 10px;\">&bull; 모집 직무</div>\r\n\r\n<div style=\"margin-bottom: 20px;\">\r\n<div style=\"font-size: 16px; color: #000; font-weight: bold;\">[피앤피시큐어] 2022년 수시채용 (솔루션 영업 부문) (신입/경력)</div>\r\n\r\n<div style=\"margin-top: 10px;\">\r\n<div>솔루션 영업 모집</div>\r\n\r\n<div>(* 부문별 자격요건 및 우대사항 그리고, 복리후생은 자사 홈페이지를 참고 부탁 드립니다.)</div>\r\n\r\n<div>&nbsp;</div>\r\n\r\n<div>1. 채널사업팀 (신입/경력)</div>\r\n\r\n<div>- 보안 솔루션 영업</div>\r\n\r\n<div>- 신규 고객 발굴 및 영업 제반 활동</div>\r\n\r\n<div>- 총판 및 채널사 관리</div>\r\n</div>\r\n</div>\r\n\r\n<div style=\"margin-bottom: 20px;\">\r\n<div style=\"font-size: 16px; color: #000; font-weight: bold;\">2022년 피앤피시큐어 수시채용 (기술본부/기술엔지니어) (신입/경력)</div>\r\n\r\n<div style=\"margin-top: 10px;\">\r\n<div>기술지원 / 기술엔지니어 모집</div>\r\n\r\n<div>(* 부문별 자격요건 및 우대사항 그리고, 복리후생은 자사 홈페이지를 참고 부탁 드립니다.)</div>\r\n\r\n<div>&nbsp;</div>\r\n\r\n<div>1. 기술본부_공통 (신입/경력)</div>\r\n\r\n<div>- 당사 보안 솔루션의 설치 / 구축 / 운영 / 정기 유지보수 지원</div>\r\n\r\n<div>&nbsp;</div>\r\n\r\n<div>2. 품질보증 (신입/경력)</div>\r\n\r\n<div>: 소프트웨어 제품 검증</div>\r\n\r\n<div>- 소프트웨어 제품 검증 계획 수립 및 수행</div>\r\n\r\n<div>- 유관부서와의 업무 협의 및 조율</div>\r\n\r\n<div>- 소프트웨어 검증 자동화</div>\r\n</div>\r\n</div>\r\n\r\n<div style=\"margin-bottom: 20px;\">\r\n<div style=\"font-size: 16px; color: #000; font-weight: bold;\">2022년 피앤피시큐어 수시채용(정보보안기술연구소/연구개발) (신입/경력)</div>\r\n\r\n<div style=\"margin-top: 10px;\">\r\n<div>연구개발 / 개발자 모집</div>\r\n\r\n<div>(* 부문별 자격요건 및 우대사항 그리고, 복리후생은 자사 홈페이지를 참고 부탁 드립니다.)</div>\r\n\r\n<div>&nbsp;</div>\r\n\r\n<div>1. Linux C/C++ 개발 (신입/경력)</div>\r\n\r\n<div>- Linux 기반 자사 솔루션 개발 및 유지보수</div>\r\n\r\n<div>&nbsp;</div>\r\n\r\n<div>2. Unix/Linux 커널 개발 (신입/경력)</div>\r\n\r\n<div>- 자사 솔루션 커널 개발</div>\r\n\r\n<div>&nbsp;</div>\r\n\r\n<div>3. Web 프로그램 개발 (신입/경력)</div>\r\n\r\n<div>- JAVA 기반 자사 웹 솔루션 개발 및 유지보수</div>\r\n\r\n<div>&nbsp;</div>\r\n\r\n<div>4. 시스템 연계 개발 (신입/경력)</div>\r\n\r\n<div>-자사 솔루션과 타사 시스템 연계/연동</div>\r\n\r\n<div>&nbsp;</div>\r\n\r\n<div>4. 윈도우 응용프로그램 개발 (신입/경력)</div>\r\n\r\n<div>- 윈도우 기반 자사 솔루션 개발 및 유지보수</div>\r\n</div>\r\n</div>\r\n</div>\r\n\r\n<div style=\"padding: 6%;\">\r\n<div style=\"font-size: 16px; color: #000; font-weight: bold; margin-bottom: 10px;\">&bull; 근무환경</div>\r\n\r\n<div style=\"margin-bottom: 20px;\">\r\n<div>&lt;&lt; 공통 자격요건 &gt;&gt;</div>\r\n\r\n<div>* 학력 무관(신입의 경우, 졸업예정자 지원가능)</div>\r\n\r\n<div>* 병역필 또는 면제자</div>\r\n\r\n<div>* 해외여행에 결격 사유가 없는 분</div>\r\n\r\n<div>* 2022년 10월경 서울특별시 마곡동 R&amp;D센터 이전 예정</div>\r\n\r\n<div>&nbsp;</div>\r\n\r\n<div>&lt;&lt; 지원방법 및 접수기간 &gt;&gt;</div>\r\n\r\n<div>* 지원 방법 : ㈜피앤피시큐어 홈페이지(https://www.pnpsecure.com/wp/05_3_download/)에서 지원서 작성 후 메일 접수</div>\r\n\r\n<div>* 접수처 : pnp-recruit@pnpsecure.com</div>\r\n\r\n<div>* 접수시 유의사항 : 메일 제목을 다음과 같이 기재 부탁 드립니다. [모집부문_성명] ex) 기술본부_공통_신입_홍길동</div>\r\n\r\n<div>* 접수 기간 : 채용 마감일까지 (채용 기간 중에도 인력 채용 완료되면 조기 마감)</div>\r\n\r\n<div>&nbsp;</div>\r\n\r\n<div>&lt;&lt; 전형절차 &gt;&gt;</div>\r\n\r\n<div>서류전형 ▶온라인 인/적성 검사 ▶1차 면접 ▶ 2차 면접 ▶ 최종 합격</div>\r\n\r\n<div>* 각 전형의 결과를 메일로만 안내하고 있습니다. 지원 후 메일 확인 부탁 드립니다.</div>\r\n\r\n<div>* 입사 지원 순서에 따라서 개인별로 채용 프로세스를 진행하므로, 채용이 완료되면 마감일 이전에 채용은 마감될 수 있습니다.</div>\r\n\r\n<div>* 온라인 인/적성 검사는 서류 전형 합격자에 한해서 별도로 안내 드립니다.</div>\r\n\r\n<div>&nbsp;</div>\r\n\r\n<div>&lt;&lt; 기타사항 &gt;&gt;</div>\r\n\r\n<div>* 당사 소개 및 기타 자세한 사항은 공식 홈페이지(http://www.pnpsecure.com)에서 확인 부탁 드립니다.</div>\r\n\r\n<div>* 현재, 근무지는 경기도 판교 플레이뮤지엄(Play Museum)이나 2022년 10월경 서울특별시 마곡동 R&amp;D센터 이전 예정입니다.</div>\r\n\r\n<div>* 제출서류에 허위기재 또는 기재착오, 구비서류 미제출 등으로 인한 불이익은 응시자 본인의 책임으로 합니다.</div>\r\n\r\n<div>* 제출서류나 각종 증명서의 기재내용이 허위일 경우, 응시를 무효로 하며 합격을 취소합니다.</div>\r\n</div>\r\n\r\n<div style=\"font-size: 16px; color: #000; font-weight: bold; margin-bottom: 10px;\">&bull; 접수 경로</div>\r\n\r\n<div style=\"margin-bottom: 20px;\">pnp-recruit@pnpsecure.com</div>\r\n\r\n<div style=\"font-size: 16px; color: #000; font-weight: bold; margin-bottom: 10px;\">&bull; 제출 서류</div>\r\n\r\n<div style=\"margin-bottom: 20px;\">입사지원서(신입,경력)</div>\r\n\r\n<div style=\"font-size: 16px; color: #000; font-weight: bold; margin-bottom: 10px;\">&bull; 문의처</div>\r\n\r\n<div>경영관리팀 / 031-8038-4053 / pnp-recruit@pnpsecure.com</div>\r\n</div>\r\n</div>\r\n"
  },
  {
  "id": 42126,
  "name": "에이피알",
  "image": "https://daoift3qrrnil.cloudfront.net/employment_companies/images/000/042/126/original/_EB_A6_AC_EB_89_B4_EC_96_BC_CI_281_29_blog.png?1613380691",
  "start_time": "2022-02-15T18:00:00.000+09:00",
  "end_time": "2022-02-28T23:59:00.000+09:00",
  "content": "<div><img src=\"https://daoift3qrrnil.cloudfront.net/content_images/images/000/061/854/original/%ED%92%88%EC%A7%88%EA%B4%80%EB%A6%AC_%EC%9D%B8%ED%84%B4.jpg?1613380104\" style=\"‘max-width:\" /></div>\r\n"
  },
  {
  "id": 42140,
  "name": "트레이",
  "image": "https://daoift3qrrnil.cloudfront.net/employment_companies/images/000/042/140/original/_ED_8A_B8_EB_A0_88_EC_9D_B4__EB_A1_9C_EA_B3_A0.png?1613442656",
  "start_time": "2022-02-16T00:00:00.000+09:00",
  "end_time": "2022-03-01T23:59:00.000+09:00",
  "content": "<div><img src=\"https://daoift3qrrnil.cloudfront.net/content_images/images/000/061/901/original/210301_%ED%8A%B8%EB%A0%88%EC%9D%B4_%EC%B1%84%EC%9A%A9%EA%B3%B5%EA%B3%A0_%EB%94%94%EC%A7%80%ED%84%B8PR%EC%8B%A0%EC%9E%85%EC%9D%B8%ED%84%B4.png?1613440496\" style=\"‘max-width:\" /></div>\r\n"
  },
  {
  "id": 42162,
  "name": "교보핫트랙스",
  "image": "https://img1.daumcdn.net/thumb/R1280x0/?scode=mtistory2&fname=https%3A%2F%2Fblog.kakaocdn.net%2Fdn%2FWQzB8%2FbtqF1nvchMI%2FkkJhnK1vWfkoeUp721t8m0%2Fimg.jpg",
  "start_time": "2022-02-16T17:48:00.000+09:00",
  "end_time": "2022-02-22T23:59:00.000+09:00",
  "content": "<p style=\"text-align: center;\"><img alt=\"\" src=\"https://daoift3qrrnil.cloudfront.net/home/ec2-user/jasoseol/public/ckeditor_assets/pictures/55734/content_rq.png\" style=\"width: 800px; height: 2088px;\" /></p>\r\n"
  },
  {
  "id": 42328,
  "name": "동국제약",
  "image": "https://daoift3qrrnil.cloudfront.net/employment_companies/images/000/042/328/original/%E1%84%83%E1%85%A9%E1%86%BC%E1%84%80%E1%85%AE%E1%86%A8%E1%84%8C%E1%85%A6%E1%84%8B%E1%85%A3%E1%86%A8.gif?1614047545",
  "start_time": "2022-02-23T11:29:00.000+09:00",
  "end_time": "2022-03-03T23:59:00.000+09:00",
  "content": "<p style=\"text-align: center;\"><img alt=\"\" src=\"https://daoift3qrrnil.cloudfront.net/home/ec2-user/jasoseol/public/ckeditor_assets/pictures/55814/content_19.png\" style=\"width: 800px; height: 5161px;\" /></p>\r\n"
  },
  {
  "id": 42329,
  "name": "데상트코리아",
  "image": "https://daoift3qrrnil.cloudfront.net/employment_companies/images/000/042/329/original/open-uri20220223-18192-20hjzu?1614049811",
  "start_time": "2022-02-23T00:00:00.000+09:00",
  "end_time": "2022-03-30T23:59:00.000+09:00",
  "content": "<p style=\"text-align: center;\"><img alt=\"\" src=\"https://daoift3qrrnil.cloudfront.net/home/ec2-user/jasoseol/public/ckeditor_assets/pictures/55815/content_3.png\" style=\"width: 800px; height: 506px;\" /></p>\r\n"
  },
  {
  "id": 42331,
  "name": "우체국시설관리단",
  "image": "https://daoift3qrrnil.cloudfront.net/employment_companies/images/000/042/331/original/JK_Co_aaaaa207334.png?1614056524",
  "start_time": "2022-02-23T13:58:00.000+09:00",
  "end_time": "2022-03-09T18:00:00.000+09:00",
  "content": "<p style=\"text-align: center;\"><img alt=\"\" src=\"https://daoift3qrrnil.cloudfront.net/home/ec2-user/jasoseol/public/ckeditor_assets/pictures/55816/content_.png.\" style=\"width: 723px; height: 4423px;\" /></p>\r\n"
  },
  {
  "id": 42334,
  "name": "OCI",
  "image": "https://daoift3qrrnil.cloudfront.net/employment_companies/images/000/042/334/original/OCI_CI.jpg?1614061435",
  "start_time": "2022-02-19T00:00:00.000+09:00",
  "end_time": "2022-03-09T13:00:00.000+09:00",
  "content": "<div><img src=\"https://daoift3qrrnil.cloudfront.net/content_images/images/000/062/408/original/0.%ED%86%B5%ED%95%A9.jpg?1614044807\" style=\"‘max-width:\" /></div>\r\n"
  },
  {
  "id": 42457,
  "name": "버킷플레이스(오늘의집)",
  "image": "https://daoift3qrrnil.cloudfront.net/employment_companies/images/000/042/457/original/_EB_A1_9C_EA_B3_A0.png?1614648693",
  "start_time": "2022-02-26T10:00:00.000+09:00",
  "end_time": "2022-03-05T10:08:00.000+09:00",
  "content": "<div style=\"border: 1px solid #ddd; color: #333; font-size: 15px; word-break: break-word;\">\n  <div style=\"padding: 6%;\">\n    <div style=\"border: 1px solid #ddd; background: #fafafa; padding: 10px; text-align: center; font-size: 20px; color: #000; font-weight: bold;\">[오늘의집] CRM 마케터 (인턴) - 3개월</div>\n    <div style=\"display: flex; justify-content: center; align-items: center; height: 150px; margin: 14% auto;\"><img src=\"https://daoift3qrrnil.cloudfront.net/business_employment_companies/images/000/006/975/original/_EB_A1_9C_EA_B3_A0.png?1614648707\" style=\"max-height:120px; max-width:40% !important;\" /></div>\n    <div style=\"color: #000;\"><div>‘누구나 예쁜집에 살 수 있어’</div><div>&nbsp</div><div>우리는 올인원 라이프스타일 플랫폼 [오늘의집]을 통해 집을 꾸미는 방식을 새롭게 정의합니다.</div><div>인테리어 가이드/정보부터 쇼핑, 시공까지 인테리어와 관련된 모든 서비스 영역을 온라인으로 제공하고 있습니다.</div></div>\n  </div>\n\n  <div style=\"padding: 6%; border-top: 1px solid #ddd; border-bottom: 1px solid #ddd;\">\n    <div style=\"font-size: 16px; color: #000; font-weight: bold; margin-bottom: 10px;\">• 모집 직무</div>\n      <div style=\"margin-bottom: 20px;\">\n        <div style=\"font-size: 16px; color: #000; font-weight: bold;\">CRM 마케터 (인턴)</div>\n        <div style=\"margin-top: 10px;\"><div>1. 팀 소개</div><div>마케팅팀은 누적 1천만 다운로드 국민앱을 넘어 인테리어가 필요한 순간 오늘의집을 모두 찾아오게 한다는 팀 미션을 가지고 일하고 있습니다. 오늘의집 서비스를 다양한 사용자에게 알릴 수 있는 SNS 채널 운영, 퍼포먼스 광고, 오늘의집 브랜드 관리, CRM 등 다양한 마케팅 역할을 담당하는 구성원들이 섞여 시너지를 내고 있습니다. 구성원들 모두가 서로 동기 부여하며, 몰입해서 치열하게 일하는 팀 중에 하나라고 생각합니다. 서비스의 빠른 성장에 기여 할 수 있는 일이 많이 있고, 실제 성취감 또한 크게 느낄 수 있는 팀이라고 자신합니다. \"We Are Greater Than I\" 이라는 생각으로, 2022년 또 한걸음 더 나아가기 위해 함께 할 동료를 찾고 있습니다. 함께 team work를 만들어 갈 분들 많이 지원해주세요!</div><div>&nbsp</div><div>2. 주요업무</div><div>· 오늘의집 콘텐츠/커머스/시공 서비스를 회원들에게 소개하고 앱 유입을 유도하는 CRM 캠페인을 운영합니다.</div><div>· 특히, 기존 유저의 인테리어 라이프 사이클을 고려해 구매 리텐션 및 Basket Size 향상을 위한 캠페인을 운영합니다.</div><div>- 오늘의집 내 기획된 CRM 캠페인을 실제 운영하면서 성과를 최적화 하는 업무를 담당합니다.</div><div>- 커머스 CRM 캠페인의 유형을 익히고, 다양한 채널 (브레이즈, 이메일, 플러스친구, LMS) 운영 경험을 쌓게 됩니다.</div><div>- BS 향상을 위한 간편결제 혜택을 운영하며, 캠페인 AB test 진행을 통한 성과를 개선합니다.</div><div>- 기본적인 SQL, 엑셀을 활용할 수 있다면 성과 비교 분석을 통해 최적화 실험을 스스로 진행 할 수 있습니다. \t</div><div>&nbsp</div><div>3. 자격요건</div><div>- 데이터에 기반해 성과를 분석하고 커뮤니케이션 할 수 있는 역량이 있는 분</div><div>- 엑셀, SQL 등을 통해 데이터를 원하는 결과물로 가공할 수 있는 분</div><div>- 유저의 관점에서 어떤 것을 궁금해하고 좋아할 지 생각 &gt; 타겟/소재 실험 &gt; 검증의 사이클이 즐거운 분\t\t</div><div>&nbsp</div><div>4. 우대사항</div><div>- Google Analytics, SQL 등 분석 관련 스킬 및 경험을 보유하신 분</div><div>- 꼼꼼하고 실수 없는 성격을 보유하신 분</div><div>- 인테리어 비즈니스에 대한 이해와 관심이 있는 분</div><div>- 오늘의집의 조직 문화를 이해하고 함께 성장하고자 하는 욕구를 지닌 분</div><div>&nbsp</div><div>5. 진행절차</div><div>서류전형 &gt; 실무팀 인터뷰 &gt; 최종합격</div><div>*지원자의 이력 및 경력 사항에 따라 일부 면접 과정이 생략되거나 추가될 수 있습니다.</div></div>\n      </div>\n  </div>\n\n  <div style=\"padding: 6%;\">\n    <div style=\"font-size: 16px; color: #000; font-weight: bold; margin-bottom: 10px;\">• 근무환경</div>\n    <div style=\"margin-bottom: 20px;\"><div>- 근무형태 : 인턴</div><div>- 근무기간 : 3개월</div><div>- 근무지 : 서울 서초구 서초대로74길 4 삼성생명서초타워 27층</div></div>\n    <div style=\"font-size: 16px; color: #000; font-weight: bold; margin-bottom: 10px;\">• 접수 경로</div>\n    <div style=\"margin-bottom: 20px;\">채용사이트 접수 (https://www.bucketplace.co.kr/recruit)</div>\n    <div style=\"font-size: 16px; color: #000; font-weight: bold; margin-bottom: 10px;\">• 제출 서류</div>\n    <div style=\"margin-bottom: 20px;\">자유양식의 이력서(필수), 포트폴리오(선택), 커버레터(선택)</div>\n    <div style=\"font-size: 16px; color: #000; font-weight: bold; margin-bottom: 10px;\">• 문의처</div>\n    <div>recruit@bucketplace.net</div>\n  </div>\n</div>"
  }
]